uavro/__init__.py
uavro/core.py
uavro/reader.c
uavro/reader.cpython-35m-darwin.so
uavro/reader.pyx
uavro/tests/__init__.py
uavro/tests/test_core.py
uavro/tests/util.py
uavro-0.0.3.dist-info/DESCRIPTION.rst
uavro-0.0.3.dist-info/METADATA
uavro-0.0.3.dist-info/RECORD
uavro-0.0.3.dist-info/WHEEL
uavro-0.0.3.dist-info/metadata.json
uavro-0.0.3.dist-info/top_level.txt
