Metadata-Version: 2.0
Name: uavro
Version: 0.0.3
Summary: Cython-optimized reader for tabular Avro data
Home-page: https://github.com/martindurant/uavro/
Author: Martin Durant
Author-email: mdurant@continuum.io
License: Apache License 2.0
Platform: UNKNOWN
Classifier: Development Status :: 3 - Alpha
Classifier: Intended Audience :: Developers
Classifier: Intended Audience :: System Administrators
Classifier: License :: OSI Approved :: Apache Software License
Classifier: Programming Language :: Python
Classifier: Programming Language :: Python :: 2.7
Classifier: Programming Language :: Python :: 3
Classifier: Programming Language :: Python :: 3.4
Classifier: Programming Language :: Python :: 3.5
Classifier: Programming Language :: Python :: 3.6
Classifier: Programming Language :: Python :: Implementation :: CPython
Requires-Dist: cython
Requires-Dist: fastparquet
Requires-Dist: numpy (>=1.11)
Requires-Dist: pandas
